nlp_text_clean/__init__.py
nlp_text_clean/cleaner.py
nlp_text_clean-0.1.4.dist-info/licenses/LICENSE
nlp_text_clean-0.1.4.dist-info/METADATA
nlp_text_clean-0.1.4.dist-info/WHEEL
nlp_text_clean-0.1.4.dist-info/top_level.txt
nlp_text_clean-0.1.4.dist-info/RECORD
