Metadata-Version: 2.4
Name: nlp-text-clean
Version: 0.1.4
Summary: A simple and configurable text preprocessing library for NLP tasks.
Author-email: Santhosh Bora <borasanthosh921@gmail.com>
License-Expression: MIT
Project-URL: Homepage, https://github.com/santhoshreddybora/nlp-text-clean
Project-URL: Bug Tracker, https://github.com/santhoshreddybora/nlp-text-clean/issues
Keywords: nlp,text-cleaning,preprocessing,stopwords,lemmatization
Classifier: Development Status :: 3 - Alpha
Classifier: Intended Audience :: Developers
Classifier: Programming Language :: Python :: 3
Classifier: Programming Language :: Python :: 3.8
Classifier: Programming Language :: Python :: 3.9
Classifier: Programming Language :: Python :: 3.10
Classifier: Programming Language :: Python :: 3.11
Classifier: Topic :: Text Processing :: Linguistic
Requires-Python: >=3.8
License-File: LICENSE
Requires-Dist: nltk>=3.8
Provides-Extra: nlp
Requires-Dist: spacy>=3.0; extra == "nlp"
Dynamic: license-file
